nillip/__init__.py
nillip/nil.py
nillip/__pycache__/__init__.cpython-311.pyc
nillip/__pycache__/__init__.cpython-37.pyc
nillip/__pycache__/nil.cpython-311.pyc
nillip/__pycache__/nil.cpython-37.pyc
nillip/test/__init__.py
nillip/test/test_1.py
nillip-1.37.dist-info/METADATA
nillip-1.37.dist-info/WHEEL
nillip-1.37.dist-info/top_level.txt
nillip-1.37.dist-info/RECORD
