Metadata-Version: 2.1
Name: nillip
Version: 1.37
Summary: custom utils package for me, but feel free to use it if you want
Home-page: UNKNOWN
Author: Phillip Maire
Author-email: phillip.maire@gmail.com
License: MIT
Platform: UNKNOWN
Classifier: Programming Language :: Python :: 3
Classifier: License :: OSI Approved :: MIT License
Classifier: Operating System :: OS Independent
Requires-Python: >=3.6
Requires-Dist: opencv-python (==4.3.0.36)
Requires-Dist: matplotlib (==3.1.3)
Requires-Dist: pytz (==2019.3)
Requires-Dist: tqdm (==4.42.1)
Requires-Dist: numpy (==1.21.6)
Requires-Dist: natsort (==7.1.1)
Requires-Dist: h5py (==2.10.0)
Requires-Dist: pandas (==1.0.1)
Requires-Dist: scipy (==1.4.1)
